Metadata-Version: 1.1
Name: dailypy
Version: 0.0.5
Summary: A useful library used everyday
Home-page: UNKNOWN
Author: Jack Huang
Author-email: jackhuang.wz@gmail.com
License: MIT
Keywords: Tools
Platform: UNKNOWN
Classifier: Development Status :: 5 - Production/Stable
Classifier: Intended Audience :: Education
Classifier: License :: OSI Approved :: MIT License
Classifier: Programming Language :: Python :: 3
